pyele/VERSION
pyele/__init__.py
pyele-0.0.0.dev0.dist-info/LICENSE
pyele-0.0.0.dev0.dist-info/METADATA
pyele-0.0.0.dev0.dist-info/WHEEL
pyele-0.0.0.dev0.dist-info/top_level.txt
pyele-0.0.0.dev0.dist-info/RECORD
