Metadata-Version: 2.1
Name: pyele
Version: 0.0.0.dev0
Summary: A python library to create and operate power systems.
Author-email: Yan Zhang <dev.claude.yan.zhang@gmail.com>
License: MIT License
Project-URL: Homepage, https://github.com/claudezss/power-system
Project-URL: Bug Tracker, https://github.com/claudezss/power-system/issues
Keywords: python,power system,power grid
Classifier: Development Status :: 3 - Alpha
Classifier: Programming Language :: Python :: 3
Classifier: License :: OSI Approved :: MIT License
Classifier: Operating System :: OS Independent
Classifier: Topic :: Software Development :: Libraries
Requires-Python: >=3.10
License-File: LICENSE
Requires-Dist: pandas
Provides-Extra: dev
Requires-Dist: pre-commit ; extra == 'dev'
Provides-Extra: doc
Requires-Dist: sphinx ; extra == 'doc'
Requires-Dist: myst-parser ; extra == 'doc'
Requires-Dist: wheel ; extra == 'doc'
Requires-Dist: ipython ; extra == 'doc'
Requires-Dist: sphinx-multiversion ; extra == 'doc'
Provides-Extra: test
Requires-Dist: pytest ; extra == 'test'
Requires-Dist: pytest-cov ; extra == 'test'
